phasegen/__init__.py
phasegen/coalescent_models.py
phasegen/comparison.py
phasegen/demography.py
phasegen/distributions.py
phasegen/expm.py
phasegen/inference.py
phasegen/lineage.py
phasegen/locus.py
phasegen/norms.py
phasegen/rewards.py
phasegen/serialization.py
phasegen/settings.py
phasegen/spectrum.py
phasegen/state_space.py
phasegen/state_space_old.py
phasegen/utils.py
phasegen/visualization.py
phasegen-1.0.2.dist-info/LICENSE
phasegen-1.0.2.dist-info/METADATA
phasegen-1.0.2.dist-info/WHEEL
phasegen-1.0.2.dist-info/RECORD
