Metadata-Version: 2.3
Name: phasegen
Version: 1.0.2
Summary: Computation and inference on exact solutions of coalescent distributions under diverse demographic scenarios.
License: MIT
Author: Sendrowski
Author-email: sendrowski.janek@gmail.com
Requires-Python: >=3.10,<3.13
Classifier: License :: OSI Approved :: MIT License
Classifier: Programming Language :: Python :: 3
Classifier: Programming Language :: Python :: 3.10
Classifier: Programming Language :: Python :: 3.11
Classifier: Programming Language :: Python :: 3.12
Requires-Dist: fastdfe (>=1.1.5)
Requires-Dist: jsonpickle (>=3.0.4,<4.0.0)
Requires-Dist: matplotlib (>=3.8.4,<4.0.0)
Requires-Dist: multiprocess (>=0.70.16,<0.71.0)
Requires-Dist: numpy (>=1.26.4,<2.0.0)
Requires-Dist: pandas (>=2.2.2,<3.0.0)
Requires-Dist: pyyaml (>=6.0.1,<7.0.0)
Requires-Dist: scipy (>=1.13.0,<2.0.0)
Requires-Dist: seaborn (>=0.13.2,<0.14.0)
Requires-Dist: tqdm (>=4.66.2,<5.0.0)
Requires-Dist: typing-extensions (>=4.11.0,<5.0.0)
